yoki5/__init__.py
yoki5/_pandas.py
yoki5/attrs.py
yoki5/base.py
yoki5/mixins.py
yoki5/multi.py
yoki5/py.typed
yoki5/repack.py
yoki5/types.py
yoki5/utilities.py
yoki5-0.1.2.dist-info/METADATA
yoki5-0.1.2.dist-info/WHEEL
yoki5-0.1.2.dist-info/licenses/LICENSE
yoki5-0.1.2.dist-info/RECORD
