Metadata-Version: 2.4
Name: yoki5
Version: 0.1.2
Summary: Wrapper around h5py to give easier interface around complex files.
Project-URL: homepage, https://github.com/lukasz-migas/yoki5
Project-URL: repository, https://github.com/lukasz-migas/yoki5
Author-email: "Lukasz G. Migas" <lukas.migas@yahoo.com>
License: BSD 3-Clause License
License-File: LICENSE
Classifier: Development Status :: 3 - Alpha
Classifier: License :: OSI Approved :: BSD License
Classifier: Natural Language :: English
Classifier: Programming Language :: Python :: 3
Classifier: Programming Language :: Python :: 3.9
Classifier: Programming Language :: Python :: 3.10
Classifier: Programming Language :: Python :: 3.11
Classifier: Typing :: Typed
Requires-Python: >=3.8
Requires-Dist: h5py
Requires-Dist: hdf5plugin
Requires-Dist: koyo
Requires-Dist: loguru
Requires-Dist: natsort
Requires-Dist: scipy
Provides-Extra: all
Requires-Dist: pandas; extra == 'all'
Provides-Extra: dev
Requires-Dist: ipython; extra == 'dev'
Requires-Dist: mypy; extra == 'dev'
Requires-Dist: pdbpp; extra == 'dev'
Requires-Dist: pre-commit; extra == 'dev'
Requires-Dist: pytest-cov; extra == 'dev'
Requires-Dist: pytest>=6.0; extra == 'dev'
Requires-Dist: rich; extra == 'dev'
Requires-Dist: ruff; extra == 'dev'
Requires-Dist: yoki[all]; extra == 'dev'
Provides-Extra: df
Requires-Dist: pandas; extra == 'df'
Provides-Extra: test
Requires-Dist: pytest-cov; extra == 'test'
Requires-Dist: pytest>=6.0; extra == 'test'
Requires-Dist: yoki[all]; extra == 'test'
